xotes/__init__.py
xotes/__main__.py
xotes/__version__.py
xotes/db.py
xotes/note.py
xotes/store.py
xotes/util.py
xotes-0.1.0.dist-info/COPYING
xotes-0.1.0.dist-info/COPYING-GPL-3
xotes-0.1.0.dist-info/COPYING~
xotes-0.1.0.dist-info/METADATA
xotes-0.1.0.dist-info/WHEEL
xotes-0.1.0.dist-info/entry_points.txt
xotes-0.1.0.dist-info/top_level.txt
xotes-0.1.0.dist-info/RECORD
