Metadata-Version: 2.1
Name: xotes
Version: 0.1.0
Summary: personal note management system.
Home-page: https://gitlab.com/jrollins/xotes
Author: Jameson Graef Rollins
Author-email: jrollins@finestructure.net
License: GPL-3.0-or-later
Platform: UNKNOWN
Classifier: License :: OSI Approved :: GNU General Public License v3 or later (GPLv3+)
Classifier: Development Status :: 4 - Beta
Classifier: Intended Audience :: End Users/Desktop
Classifier: Natural Language :: English
Classifier: Operating System :: OS Independent
Classifier: Programming Language :: Python
Requires-Dist: dateutil
Requires-Dist: git
Requires-Dist: pyyaml
Requires-Dist: urwid
Requires-Dist: xapian
